telegram_export_channel_links.py
telegram_export_channel_links-0.0.3.dist-info/LICENSE
telegram_export_channel_links-0.0.3.dist-info/METADATA
telegram_export_channel_links-0.0.3.dist-info/WHEEL
telegram_export_channel_links-0.0.3.dist-info/entry_points.txt
telegram_export_channel_links-0.0.3.dist-info/top_level.txt
telegram_export_channel_links-0.0.3.dist-info/RECORD
