Metadata-Version: 2.1
Name: telegram-export-channel-links
Version: 0.0.3
Summary: Export public channel and group links of telegram account.
Home-page: https://github.com/Layerex/telegram-export-channel-links
Author: Layerex
Author-email: layerex@dismail.de
License: UNKNOWN
Platform: UNKNOWN
Classifier: Development Status :: 6 - Mature
Classifier: Environment :: Web Environment
Classifier: Programming Language :: Python :: 3
Classifier: License :: OSI Approved :: The Unlicense (Unlicense)
Classifier: Operating System :: OS Independent
Classifier: Topic :: Utilities
License-File: LICENSE
Requires-Dist: telethon
Requires-Dist: pystandardpaths
